{
  "Page_Chart": {
    "src": "ChartWidget",
    "dataProvider": {
      "url": "n2o/data/test",
      "pathMapping": {},
      "queryMapping": {}
    },
    "chart": {
      "fetchOnInit": true,
      "type": "area",
      "layout": "horizontal",
      "width": 600,
      "height": 400,
      "stackOffset": "none",
      "baseValue": "auto",
      "margin": { "top": 5, "right": 5, "bottom": 5, "left": 5 },
      "XAxis": {
        "hide": false,
        "dataKey": "name",
        "height": 30,
        "orientation": "bottom",
        "type": "category",
        "allowDecimals": true,
        "allowDataOverflow": false,
        "allowDuplicatedCategory": true,
        "tickCount": 5,
        "interval": "preserveEnd",
        "padding": {
          "left": 0,
          "right": 0
        },
        "minTickGap": 5,
        "axisLine": true,
        "tickLine": true,
        "tickSize": 6,
        "label": false
      },
      "YAxis": {
        "hide": false,
        "height": 30,
        "orientation": "left",
        "type": "number",
        "allowDecimals": true,
        "allowDataOverflow": false,
        "allowDuplicatedCategory": true,
        "tickCount": 5,
        "interval": "preserveEnd",
        "padding": {
          "left": 0,
          "right": 0
        },
        "minTickGap": 5,
        "axisLine": true,
        "tickLine": true,
        "tickSize": 6,
        "label": false
      },
      "cartesianGrid": {
        "x": 0,
        "y": 0,
        "width": 0,
        "height": 0,
        "horizontal": true,
        "vertical": true,
        "horizontalPoints": [],
        "verticalPoints": [],
        "strokeDasharray": "3 3"
      },
      "tooltip": {
        "separator": ":",
        "offset": 10,
        "filterNull": true,
        "itemStyle": {},
        "wrapperStyle": {},
        "contentStyle": {},
        "labelStyle": {},
        "viewBox": {},
        "label": null
      },
      "legend": {
        "width": null,
        "height": null,
        "layout": "horizontal",
        "align": "center",
        "verticalAlign": "bottom",
        "iconSize": 14,
        "iconType": "line",
        "margin": {},
        "wrapperStyle": {}
      },
      "areas": [
        {
          "type": "monotone",
          "dataKey": "uv",
          "legendType": "line",
          "dot": false,
          "activeDot": true,
          "label": false,
          "stroke": "#8884d8",
          "fill": "#8884d8",
          "layout": "horizontal",
          "stackId": 1
        },
        {
          "type": "monotone",
          "dataKey": "pv",
          "legendType": "line",
          "dot": false,
          "activeDot": true,
          "label": false,
          "stroke": "#82ca9d",
          "fill": "#82ca9d",
          "layout": "horizontal",
          "stackId": 1
        },
        {
          "type": "monotone",
          "dataKey": "amt",
          "legendType": "line",
          "dot": false,
          "activeDot": true,
          "label": false,
          "stroke": "#ffc658",
          "fill": "#ffc658",
          "layout": "horizontal",
          "stackId": 1
        }
      ]
    }
  }
}