{
    "src": "FormWidget",
    "toolbar": {
      "topRight": [
        {
          "buttons": [
            {
              "id": "refresh",
              "hint": "Запросить данные",
              "title": "Открыть MO",
              "confirm":{
                "modelLink": "models.resolve['Page_Form'].name",
                "text": "`\"Вы ввели \"+this`",
                "title":"Предупреждение",
                "okLabel":"Да",
                "cancelLabel":"Нет"
              }
            }
          ]
        }
      ]
    },
  "form": {
    "fetchOnInit": false,
    "fieldsets": [
      {
        "src": "StandardFieldset",
        "rows": [
          {
            "cols": [
              {
                "fields": [
                  {
                    "id": "name",
                    "src": "StandardField",
                    "label": "Имя",
                    "control": {
                      "src": "InputText"
                    }
                  }
                ]
              }
            ]
          }
        ]
      }
    ]
  }
  }