<?xml version='1.0' encoding='UTF-8'?>
<page xmlns="http://n2oapp.net/framework/config/schema/page-2.0"
      name="Список справочников" route="/refbooks">
    <regions>
        <panel place="single" header="false" collapsible="false">
            <table id="main" name="Справочники" query-id="refbooks">
                <pagination/>
                <columns>
                    <column text-field-id="name"/>
                    <column text-field-id="table_name"/>
                    <column text-field-id="create_date" sorting-direction="asc">
                        <text format="date DD.MM.YYYY"/>
                    </column>
                </columns>
                <filters place="top">
                    <row>
                        <input-text id="name"/>
                        <input-text id="table_name"/>
                    </row>
                </filters>
                <toolbar>
                    <button id="viewPage" label="Просмотр на странице">
                        <open-page page-id="{refbooks_main_id}" detail-field-id="pageName"/>
                    </button>
                    <button id="viewModal" label="Просмотр в модальном окне">
                        <show-modal page-id="{refbooks_main_id}" detail-field-id="pageName"/>
                    </button>
                </toolbar>
            </table>
        </panel>
    </regions>
</page>